{
  "Name": "SR-Latch",
  "Colour": "#FB5D5D",
  "InputPins": [
    {
      "Name": "S",
      "ID": 1484113429,
      "PositionY": 2.76851845,
      "ColourThemeName": "Red"
    },
    {
      "Name": "R",
      "ID": 392071745,
      "PositionY": -0.8981481,
      "ColourThemeName": "Red"
    }
  ],
  "OutputPins": [
    {
      "Name": "Qc",
      "ID": 295360207,
      "PositionY": -0.9259263,
      "ColourThemeName": "Red"
    },
    {
      "Name": "Q",
      "ID": 919194831,
      "PositionY": 2.518518,
      "ColourThemeName": "Red"
    }
  ],
  "SubChips": [
    {
      "Name": "OR",
      "ID": 1577492922,
      "Points": [
        {
          "X": -3.60185218,
          "Y": 2.83333325
        }
      ],
      "Data": null
    },
    {
      "Name": "NOT",
      "ID": 718340210,
      "Points": [
        {
          "X": -1.13888907,
          "Y": 2.76851845
        }
      ],
      "Data": null
    },
    {
      "Name": "OR",
      "ID": 1704041106,
      "Points": [
        {
          "X": -3.50000024,
          "Y": -0.9074074
        }
      ],
      "Data": null
    },
    {
      "Name": "NOT",
      "ID": 2138239204,
      "Points": [
        {
          "X": -1.240741,
          "Y": -0.87962985
        }
      ],
      "Data": null
    }
  ],
  "Connections": [
    {
      "Source": {
        "PinType": 4,
        "SubChipID": 1704041106,
        "PinID": 2131571044
      },
      "Target": {
        "PinType": 3,
        "SubChipID": 2138239204,
        "PinID": 0
      },
      "WirePoints": [
        {
          "X": -3.05000019,
          "Y": -0.9074074
        },
        {
          "X": -1.790741,
          "Y": -0.87962985
        }
      ],
      "ColourThemeName": "Red"
    },
    {
      "Source": {
        "PinType": 4,
        "SubChipID": 1577492922,
        "PinID": 2131571044
      },
      "Target": {
        "PinType": 3,
        "SubChipID": 718340210,
        "PinID": 0
      },
      "WirePoints": [
        {
          "X": -3.15185213,
          "Y": 2.83333325
        },
        {
          "X": -1.688889,
          "Y": 2.76851845
        }
      ],
      "ColourThemeName": "Red"
    },
    {
      "Source": {
        "PinType": 1,
        "SubChipID": 0,
        "PinID": 1484113429
      },
      "Target": {
        "PinType": 3,
        "SubChipID": 1577492922,
        "PinID": 236404678
      },
      "WirePoints": [
        {
          "X": -7.837778,
          "Y": 2.76851845
        },
        {
          "X": -6.833334,
          "Y": 2.76851845
        },
        {
          "X": -6.851852,
          "Y": 2.97222185
        },
        {
          "X": -4.051852,
          "Y": 2.95333314
        }
      ],
      "ColourThemeName": "Red"
    },
    {
      "Source": {
        "PinType": 4,
        "SubChipID": 1704041106,
        "PinID": 2131571044
      },
      "Target": {
        "PinType": 3,
        "SubChipID": 2138239204,
        "PinID": 0
      },
      "WirePoints": [
        {
          "X": -3.05000019,
          "Y": -0.9074074
        },
        {
          "X": -1.790741,
          "Y": -0.87962985
        }
      ],
      "ColourThemeName": "Red"
    },
    {
      "Source": {
        "PinType": 4,
        "SubChipID": 2138239204,
        "PinID": 1
      },
      "Target": {
        "PinType": 3,
        "SubChipID": 1577492922,
        "PinID": 93189383
      },
      "WirePoints": [
        {
          "X": -0.690741,
          "Y": -0.87962985
        },
        {
          "X": 0.5277782,
          "Y": -0.851852
        },
        {
          "X": 0.5092589,
          "Y": 0.490740538
        },
        {
          "X": -4.90740776,
          "Y": 0.5000001
        },
        {
          "X": -4.89814854,
          "Y": 2.731481
        },
        {
          "X": -4.051852,
          "Y": 2.71333337
        }
      ],
      "ColourThemeName": "Red"
    },
    {
      "Source": {
        "PinType": 1,
        "SubChipID": 0,
        "PinID": 392071745
      },
      "Target": {
        "PinType": 3,
        "SubChipID": 1704041106,
        "PinID": 93189383
      },
      "WirePoints": [
        {
          "X": -7.837778,
          "Y": -0.8981481
        },
        {
          "X": -5.712963,
          "Y": -0.8981481
        },
        {
          "X": -5.703704,
          "Y": -1.04629636
        },
        {
          "X": -3.95000029,
          "Y": -1.02740741
        }
      ],
      "ColourThemeName": "Red"
    },
    {
      "Source": {
        "PinType": 4,
        "SubChipID": 718340210,
        "PinID": 1
      },
      "Target": {
        "PinType": 3,
        "SubChipID": 1704041106,
        "PinID": 236404678
      },
      "WirePoints": [
        {
          "X": -0.588889062,
          "Y": 2.76851845
        },
        {
          "X": 0.435184926,
          "Y": 2.7962966
        },
        {
          "X": 0.472222447,
          "Y": 0.935184956
        },
        {
          "X": -4.63888931,
          "Y": 0.935184956
        },
        {
          "X": -4.64814854,
          "Y": -0.768518448
        },
        {
          "X": -3.95000029,
          "Y": -0.7874074
        }
      ],
      "ColourThemeName": "Red"
    },
    {
      "Source": {
        "PinType": 4,
        "SubChipID": 718340210,
        "PinID": 1
      },
      "Target": {
        "PinType": 2,
        "SubChipID": 0,
        "PinID": 295360207
      },
      "WirePoints": [
        {
          "X": -0.588889062,
          "Y": 2.76851845
        },
        {
          "X": 0.23202467,
          "Y": 2.79078579
        },
        {
          "X": 7.23148155,
          "Y": 2.80555534
        },
        {
          "X": 7.21296358,
          "Y": 2.685185
        },
        {
          "X": 7.837778,
          "Y": -0.9259263
        }
      ],
      "ColourThemeName": "Red"
    },
    {
      "Source": {
        "PinType": 4,
        "SubChipID": 2138239204,
        "PinID": 1
      },
      "Target": {
        "PinType": 2,
        "SubChipID": 0,
        "PinID": 919194831
      },
      "WirePoints": [
        {
          "X": -0.690741,
          "Y": -0.87962985
        },
        {
          "X": 5.08333349,
          "Y": -0.8981481
        },
        {
          "X": 5.11111164,
          "Y": 2.52777767
        },
        {
          "X": 7.740741,
          "Y": 2.52777767
        },
        {
          "X": 7.837778,
          "Y": 2.518518
        }
      ],
      "ColourThemeName": "Red"
    }
  ]
}